COPYING
COPYING.LESSER
MANIFEST.in
README.txt
THANKS.txt
autoclosingqueue.py
nonblockingloghandler.py
setup.py
nonblockingloghandler.egg-info/PKG-INFO
nonblockingloghandler.egg-info/SOURCES.txt
nonblockingloghandler.egg-info/dependency_links.txt
nonblockingloghandler.egg-info/top_level.txt
test/test_all_nonblockingloghandler.py
test/test_autoclosing_queue.py
test/test_autoclosing_queue_autocloses.py
test/test_nonblockingloghandler_stresstest.py
test/test_nonblockingloghandler_termination_subtest1.py
test/test_nonblockingloghandler_termination_subtest2.py
test/test_nonblockingloghandler_termination_subtest3.py
test/test_nonblockingloghandler_termination_tests.py
test/test_nonblockingloghandler_units.py