Metadata-Version: 1.0
Name: nonblockingloghandler
Version: 1.0.0
Summary: Nonblocking Logging Handler for Python Logging
Home-page: http://somethinkodd.com/nonblockingloghandler
Author: Somethinkodd Development Team
Author-email: logging@somethinkodd.com
License: UNKNOWN
Platform: UNKNOWN
Classifier: Development Status :: 5 - Production/Stable
Classifier: Intended Audience :: Developers
Classifier: License :: OSI Approved :: GNU Library or Lesser General Public License (LGPL)
Classifier: Operating System :: OS Independent
Classifier: Programming Language :: Python
Classifier: Topic :: System :: Logging
